[
  {
    "url": "https://www.youtube.com/embed/HPLqDO3GFN4",
    "description": "YouTube"
  },
  {
    "url": "https://www.youtube.com/watch/videoseries?list=PLKV-LnsZiOo98i7laSg3VtwoWx6-g3Dv0",
    "description": "Playlist - Tazeta & Boogieman Sam"
  },
  {
    "url": "https://www.youtube.com/embed/8wsVOhUE2Po",
    "description": "Self-Immolate"
  },
  {
    "url": "https://www.youtube.com/embed/h16lzP3p4WM",
    "description": "Honey"
  },
  {
    "url": "https://www.youtube.com/watch?v=CgwhFCQpBiY",
    "description": "Fan Interviews"
  }
]
