[
  {
    "url": "https://archive.org/embed/kg2022-11-02?playlist=1&list_height=150",
    "description": "Official Bootleg"
  },
  {
    "url": "https://www.youtube.com/embed/videoseries?list=PLKV-LnsZiOo-N36Yxo5PmBSstqcu8nHi9",
    "description": "AUD Shot Playlist"
  },
  {
    "url": "https://www.youtube.com/embed/jZqKxdFCF1E",
    "description": "Nugs Pro Shot"
  },
  {
    "url": "https://www.youtube.com/watch?v=DHpU_b9dHQk",
    "description": "Float Along - Fill Your Lungs"
  },
  {
    "url": "https://www.youtube.com/playlist?list=PLKV-LnsZiOo-N36Yxo5PmBSstqcu8nHi9",
    "description": "9 Video Playlist - Fan Shot"
  }
]
