[
  { "year":2014, "month": 5, "day": 2, "note": "the band's first full-length show in the USA; recorded and released as Live At Levitation '14", "url": "https://kglw.net/releases/live-at-levitation-2014" },
  { "year":2016, "month": 5, "day": 1, "note": "recorded and released as Live At Levitation '16", "url": "https://kglw.net/releases/live-at-levitation-2014" },
  { "year":2016, "month": 5, "day":25, "note": "recorded and released as Live In San Francisco '16", "url": "https://kglw.net/releases/live-in-san-francisco-2016" },
  { "year":2019, "month": 7, "day":12, "note": "recorded and released as Live In Adelaide '19", "url": "https://kglw.net/releases/live-in-adelaide-2019" },
  { "year":2019, "month": 8, "day":23, "note": "recorded and released as Live In Milwaukee '19", "url": "https://kglw.net/releases/live-in-brisbane-2021" },
  { "year":2019, "month":10, "day": 8, "note": "recorded and released as (part of) Live In Brussels '19", "url": "https://kglw.net/releases/live-in-brussels-2019" },
  { "year":2019, "month":10, "day": 9, "note": "recorded and released as (part of) Live In Brussels '19", "url": "https://kglw.net/releases/live-in-brussels-2019" },
  { "year":2019, "month":10, "day":14, "note": "recorded and released as Live In Paris '19", "url": "https://kglw.net/releases/live-in-paris-2019" },
  { "year":2020, "month":10, "day": 1, "note": "recorded and released as Live In Asheville '19", "url": "https://kglw.net/releases/live-in-asheville-2019" },
  { "year":2020, "month":12, "day":24, "note": "recorded and released as Live In London '19", "url": "https://kglw.net/releases/live-in-london-2019" },
  { "year":2021, "month": 2, "day":26, "note": "recorded and released as Live In Melbourne '21", "url": "https://kglw.net/releases/live-in-melbourne-2021" },
  { "year":2021, "month":12, "day":19, "note": "recorded and released as Live In Brisbane '21", "url": "https://kglw.net/releases/live-in-brisbane-2021" },
  { "year":2022, "month": 6, "day":17, "note": "recorded and released as Live At Bonnaroo '22", "url": "https://kglw.net/releases/live-at-bonnaroo-2022" },
  { "year":2022, "month":10, "day":10, "note": "recorded and released as (part of) Live At Red Rocks '22", "url": "https://kglw.net/releases/live-at-red-rocks-22" },
  { "year":2022, "month":10, "day":11, "note": "recorded and released as (part of) Live At Red Rocks '22", "url": "https://kglw.net/releases/live-at-red-rocks-22" },
  { "year":2022, "month":11, "day": 2, "note": "recorded and released as (part of) Live At Red Rocks '22", "url": "https://kglw.net/releases/live-at-red-rocks-22" },
  {}
]
